confspawn/__init__.py
confspawn/cli.py
confspawn/documentation.md
confspawn/spawn.py
confspawn-0.6.0.dist-info/WHEEL
confspawn-0.6.0.dist-info/LICENSE
confspawn-0.6.0.dist-info/entry_points.txt
confspawn-0.6.0.dist-info/METADATA
confspawn-0.6.0.dist-info/RECORD
