Metadata-Version: 2.1
Name: confspawn
Version: 0.6.0
Summary: Easily build configuration files from templates.
License: Apache-2.0
Author: Tip ten Brink
Author-email: 75669206+tiptenbrink@users.noreply.github.com
Requires-Python: >=3.8,<4.0
Classifier: License :: OSI Approved :: Apache Software License
Classifier: Programming Language :: Python :: 3
Classifier: Programming Language :: Python :: 3.8
Classifier: Programming Language :: Python :: 3.9
Classifier: Programming Language :: Python :: 3.10
Classifier: Programming Language :: Python :: 3.11
Requires-Dist: jinja2 (>=3.1.0,<4.0.0)
Requires-Dist: tomli (>=2.0.1,<3.0.0)
Requires-Dist: typing-extensions (>=4.8.0,<5.0.0)
Project-URL: Source Code, https://github.com/tiptenbrink/confspawn
